lazygit/__init__.py
lazygit/__main__.py
lazygit/config.py
lazygit/git_operations.py
lazygit/ui/__init__.py
lazygit/ui/app.py
lazygit/ui/dialogs.py
lazygit_python-0.1.0.dist-info/METADATA
lazygit_python-0.1.0.dist-info/WHEEL
lazygit_python-0.1.0.dist-info/entry_points.txt
lazygit_python-0.1.0.dist-info/top_level.txt
lazygit_python-0.1.0.dist-info/RECORD
