Metadata-Version: 2.4
Name: lazygit-python
Version: 0.1.0
Summary: A Python clone of lazygit with TUI interface
Author-email: Jordan Diaz <jordandiazdiaz@gmail.com>
License-Expression: MIT
Project-URL: Homepage, https://github.com/jordandiazdiaz/lazygit-python
Project-URL: Bug Tracker, https://github.com/jordandiazdiaz/lazygit-python/issues
Keywords: git,terminal,tui,lazygit,version-control
Classifier: Development Status :: 3 - Alpha
Classifier: Intended Audience :: Developers
Classifier: Topic :: Software Development :: Version Control :: Git
Classifier: Operating System :: OS Independent
Classifier: Programming Language :: Python :: 3
Classifier: Programming Language :: Python :: 3.8
Classifier: Programming Language :: Python :: 3.9
Classifier: Programming Language :: Python :: 3.10
Classifier: Programming Language :: Python :: 3.11
Classifier: Programming Language :: Python :: 3.12
Requires-Python: >=3.8
Requires-Dist: textual>=0.47.0
Requires-Dist: GitPython>=3.1.40
Requires-Dist: click>=8.1.7
Requires-Dist: pyyaml>=6.0.1
